splaat/__init__.py
splaat/_version.py
splaat/utils.py
splaat/audio/__init__.py
splaat/audio/load.py
splaat/audio/prep.py
splaat/plot/__init__.py
splaat/plot/spectrogram.py
splaat/plot/textgrid.py
splaat/plot/waveform.py
splaat-0.1.0.dist-info/licenses/LICENSE
tests/__init__.py
tests/conftest.py
tests/test_load.py
tests/test_spectrogram.py
tests/data/audio/mfa.wav
tests/data/audio/mfa_michael.flac
splaat-0.1.0.dist-info/METADATA
splaat-0.1.0.dist-info/WHEEL
splaat-0.1.0.dist-info/top_level.txt
splaat-0.1.0.dist-info/RECORD
