Metadata-Version: 2.4
Name: splaat
Version: 0.1.0
Home-page: https://github.com/mmcauliffe/splaat
Author: Michael McAuliffe and Kaylynn Gunter
Author-email: michael.e.mcauliffe@gmail.com
License: MIT
Keywords: phonetics,acoustics
Classifier: Development Status :: 3 - Alpha
Classifier: Intended Audience :: Science/Research
Classifier: License :: OSI Approved :: MIT License
Classifier: Operating System :: OS Independent
Classifier: Programming Language :: Python
Classifier: Programming Language :: Python :: 3
Classifier: Topic :: Scientific/Engineering
Classifier: Topic :: Text Processing :: Linguistic
License-File: LICENSE
Requires-Dist: librosa
Requires-Dist: matplotlib
Requires-Dist: seaborn
Provides-Extra: test
Requires-Dist: pytest; extra == "test"
Dynamic: license-file
